insilico/__init__.py
insilico/functions.py
insilico/model.py
insilico/data/empty.txt
insilico/fingerprints_xml/AtomPairs2DFingerprintCount.xml
insilico/fingerprints_xml/AtomPairs2DFingerprinter.xml
insilico/fingerprints_xml/EStateFingerprinter.xml
insilico/fingerprints_xml/ExtendedFingerprinter.xml
insilico/fingerprints_xml/Fingerprinter.xml
insilico/fingerprints_xml/GraphOnlyFingerprinter.xml
insilico/fingerprints_xml/KlekotaRothFingerprintCount.xml
insilico/fingerprints_xml/KlekotaRothFingerprinter.xml
insilico/fingerprints_xml/MACCSFingerprinter.xml
insilico/fingerprints_xml/PubchemFingerprinter.xml
insilico/fingerprints_xml/SubstructureFingerprintCount.xml
insilico/fingerprints_xml/SubstructureFingerprinter.xml
insilico-0.1.2.dist-info/LICENSE
insilico-0.1.2.dist-info/METADATA
insilico-0.1.2.dist-info/WHEEL
insilico-0.1.2.dist-info/top_level.txt
insilico-0.1.2.dist-info/RECORD
