Metadata-Version: 2.1
Name: insilico
Version: 0.1.2
Summary: A Python package to process & model ChEMBL data.
Home-page: https://github.com/konstanzer/insilico
Author: Steven Newton
Author-email: steven.j.newton99@gmail.com
License: MIT
Platform: UNKNOWN
Classifier: License :: OSI Approved :: MIT License
Classifier: Topic :: Scientific/Engineering :: Chemistry
Classifier: Operating System :: MacOS :: MacOS X
Classifier: Programming Language :: Python
License-File: LICENSE
